{
    "id":  "card_jace_v2_1",
    "baseType":  "Planeswalker",
    "manaCost":  {
                     "U":  3
                 },
    "initialLoyalty":  4,
    "loyaltyAbilities":  [
                             {
                                 "cost":  1,
                                 "description":  "+1: Gana 1 vida y roba una carta.",
                                 "name":  "Análisis Mental",
                                 "type":  "plus"
                             },
                             {
                                 "cost":  2,
                                 "description":  "-2: El jugador objetivo pone las dos primeras cartas de su biblioteca en su cementerio.",
                                 "name":  "Conocimiento Olvidado",
                                 "type":  "minus"
                             },
                             {
                                 "cost":  6,
                                 "description":  "-6: Ganas un emblema con \u0027Puedes lanzar hechizos de instantáneo y conjuro de tu cementerio.\u0027",
                                 "name":  "Dominio Total",
                                 "type":  "ultimate"
                             }
                         ],
    "name":  "Jace, Telépata Rebelde",
    "text":  "Jace, Telépata Rebelde entra con 4 contadores de lealtad."
}
